RR_dummy_distributions/Binomialdistribution.py
RR_dummy_distributions/Gaussiandistribution.py
RR_dummy_distributions/Generaldistribution.py
RR_dummy_distributions/__init__.py
RR_dummy_distributions-0.2.dist-info/METADATA
RR_dummy_distributions-0.2.dist-info/WHEEL
RR_dummy_distributions-0.2.dist-info/top_level.txt
RR_dummy_distributions-0.2.dist-info/RECORD
